[
  {
    "fuses": [
      {
        "layout": {
          "top": 7.29483282674772,
          "left": 7.807486631016043,
          "width": 7.160427807486641,
          "height": 3.559270516717327
        },
        "id": "1",
        "kind": {
          "type": "fuse",
          "format": "mini",
          "amp": 10
        },
        "description": "Instrument Cluster, A/C Control Module",
        "relatedEntities": [
          "TABLERO",
          "AIRE_ACONDICIONADO",
          "COMANDO_CLIMATIZADOR"
        ],
        "individualFusePages": [
          {
            "url": "/hyundai/santa-fe/info/fusebox/2017/air-conditioning-fuse",
            "urlWithAnchor": "/hyundai/santa-fe/info/fusebox/2017/air-conditioning-fuse#problems-article",
            "title": "Air conditioning fuse",
            "problemsTitle": "View problems with the air conditioning fuse"
          }
        ]
      },
      {
        "layout": {
          "top": 7.29483282674772,
          "left": 18.93048128342246,
          "width": 7.160427807486641,
          "height": 3.559270516717327
        },
        "id": "2",
        "kind": {
          "type": "fuse",
          "format": "mini",
          "amp": 15
        },
        "description": "ACU, Passenger Occupant Detection Sensor"
      },
      {
        "layout": {
          "top": 7.29483282674772,
          "left": 30.053475935828878,
          "width": 7.160427807486641,
          "height": 3.559270516717327
        },
        "id": "3",
        "kind": {
          "type": "fuse",
          "format": "mini",
          "amp": 7.5
        },
        "description": "RR _BLOWER, AVM, AC_INVERTER_UNIT,Smart Key Control Module, BCM, Rear Seat Warmer LH/RH,Driver/Passenger Seat Warmer Module,",
        "relatedEntities": [
          "LLAVE_INTELIGENTE",
          "MODULO_CARROCERIA"
        ]
      },
      {
        "layout": {
          "top": 7.29483282674772,
          "left": 52.406417112299465,
          "width": 7.053475935828889,
          "height": 3.559270516717327
        },
        "id": "4",
        "kind": {
          "type": "fuse",
          "format": "mini",
          "amp": 7.5
        },
        "description": "Sport Mode Switch, Key Solenoid, Console Switch LH/RH,Real Power Window Switch LH/RH, Data Link Connector",
        "relatedEntities": [
          "CONECTOR_OBD"
        ]
      },
      {
        "layout": {
          "top": 7.29483282674772,
          "left": 63.52941176470588,
          "width": 7.053475935828889,
          "height": 3.559270516717327
        },
        "id": "5",
        "kind": {
          "type": "fuse",
          "format": "mini",
          "amp": 10
        },
        "description": "Not Used",
        "relatedEntities": [
          "NOT_USED_FUSE"
        ]
      },
      {
        "layout": {
          "top": 7.29483282674772,
          "left": 74.75935828877004,
          "width": 7.053475935828889,
          "height": 3.559270516717327
        },
        "id": "6",
        "kind": {
          "type": "fuse",
          "format": "mini",
          "amp": 10
        },
        "description": "BCM, Tire Pressure Monitoring Module, Electro Chromic Mirror, Driver/Passenger Door Module, Auto Light & Photo Sensor, A/C Control Module, Instrument Cluster, FRT_DRV_SEAT",
        "relatedEntities": [
          "MODULO_CARROCERIA",
          "SENSOR_PRESION_NEUMATICOS",
          "AIRE_ACONDICIONADO",
          "COMANDO_CLIMATIZADOR",
          "TABLERO"
        ],
        "individualFusePages": [
          {
            "url": "/hyundai/santa-fe/info/fusebox/2017/air-conditioning-fuse",
            "urlWithAnchor": "/hyundai/santa-fe/info/fusebox/2017/air-conditioning-fuse#problems-article",
            "title": "Air conditioning fuse",
            "problemsTitle": "View problems with the air conditioning fuse"
          }
        ]
      },
      {
        "layout": {
          "top": 15.80547112462006,
          "left": 7.807486631016043,
          "width": 7.160427807486641,
          "height": 3.711246200607905
        },
        "id": "7",
        "kind": {
          "type": "fuse",
          "format": "mini",
          "amp": 7.5
        },
        "description": "Smart Key Control Module, Immobilizer Module",
        "relatedEntities": [
          "LLAVE_INTELIGENTE",
          "INMOVILIZADOR",
          "MODULO(of=INMOVILIZADOR)"
        ]
      },
      {
        "layout": {
          "top": 15.80547112462006,
          "left": 19.037433155080212,
          "width": 7.053475935828889,
          "height": 3.559270516717327
        },
        "id": "8",
        "kind": {
          "type": "fuse",
          "format": "mini",
          "amp": 10
        },
        "description": "BCM, Instrument Cluster, Tire Pressure Monitoring Module, A/C Control Module, Driver/Passenger Door Module, ATM Shift Lever Indicator, Rear Seat Warmer LH/RH, 4WD ECU, Driver/Passenger Seat Warmer Module, MTS Module, Rear(SMART) Parking Assist Sensor LH/RH, A/V & Navigation Head Unit, Rear Parking Assist Sensor (Center)LH/RH, AMP, SAS_ESP,EPB_EXT, Electro Chromic Mirror, BSD",
        "relatedEntities": [
          "MODULO_CARROCERIA",
          "TABLERO",
          "SENSOR_PRESION_NEUMATICOS",
          "AIRE_ACONDICIONADO",
          "COMANDO_CLIMATIZADOR",
          "AMPLIFICADOR"
        ],
        "individualFusePages": [
          {
            "url": "/hyundai/santa-fe/info/fusebox/2017/air-conditioning-fuse",
            "urlWithAnchor": "/hyundai/santa-fe/info/fusebox/2017/air-conditioning-fuse#problems-article",
            "title": "Air conditioning fuse",
            "problemsTitle": "View problems with the air conditioning fuse"
          }
        ]
      },
      {
        "id": "9",
        "kind": {
          "type": "fuse",
          "format": "mini"
        },
        "layout": {
          "top": 15.80547112462006,
          "left": 30.053475935828878,
          "width": 7.160427807486641,
          "height": 3.559270516717327
        },
        "relatedEntities": []
      },
      {
        "layout": {
          "top": 15.80547112462006,
          "left": 52.406417112299465,
          "width": 7.053475935828889,
          "height": 3.711246200607905
        },
        "id": "10",
        "kind": {
          "type": "fuse",
          "format": "mini",
          "amp": 7.5
        },
        "description": "Smart Key Control Module",
        "relatedEntities": [
          "LLAVE_INTELIGENTE"
        ]
      },
      {
        "layout": {
          "top": 15.80547112462006,
          "left": 63.52941176470588,
          "width": 7.053475935828889,
          "height": 3.711246200607905
        },
        "id": "11",
        "kind": {
          "type": "fuse",
          "format": "mini",
          "amp": 15
        },
        "description": "Cargo Lamp, Vanity Lamp LH/RH, Overhead Console Lamp, Center Room Lamp, Personal Lamp LH/RH",
        "relatedEntities": [
          "LUZ_DE_CAJA"
        ]
      },
      {
        "layout": {
          "top": 15.80547112462006,
          "left": 74.75935828877004,
          "width": 7.053475935828889,
          "height": 3.559270516717327
        },
        "id": "12",
        "kind": {
          "type": "fuse",
          "format": "mini",
          "amp": 15
        },
        "description": "Audio, A/V & Navigation Head Unit, MTS Module,D_CLOCK",
        "relatedEntities": [
          "ESTEREO"
        ],
        "individualFusePages": [
          {
            "url": "/hyundai/santa-fe/info/fusebox/2017/radio-fuse",
            "urlWithAnchor": "/hyundai/santa-fe/info/fusebox/2017/radio-fuse#problems-article",
            "title": "Radio fuse",
            "problemsTitle": "View problems with the radio fuse"
          }
        ]
      },
      {
        "layout": {
          "top": 24.316109422492403,
          "left": 7.807486631016043,
          "width": 7.160427807486641,
          "height": 3.559270516717327
        },
        "id": "13",
        "kind": {
          "type": "fuse",
          "format": "mini",
          "amp": 7.5
        },
        "description": "MDPS Unit"
      },
      {
        "id": "14",
        "kind": {
          "type": "fuse",
          "format": "mini"
        },
        "layout": {
          "top": 24.316109422492403,
          "left": 19.037433155080212,
          "width": 7.053475935828889,
          "height": 3.559270516717327
        },
        "relatedEntities": []
      },
      {
        "layout": {
          "top": 24.316109422492403,
          "left": 30.053475935828878,
          "width": 7.160427807486641,
          "height": 3.559270516717327
        },
        "id": "15",
        "kind": {
          "type": "fuse",
          "format": "mini",
          "amp": 15
        },
        "description": "Steering Wheel Switch",
        "relatedEntities": [
          "COMANDOS_VOLANTE"
        ]
      },
      {
        "layout": {
          "top": 24.316109422492403,
          "left": 52.406417112299465,
          "width": 7.053475935828889,
          "height": 3.559270516717327
        },
        "id": "16",
        "kind": {
          "type": "fuse",
          "format": "mini",
          "amp": 15
        },
        "description": "FRT FOG LAMP LH/RH"
      },
      {
        "layout": {
          "top": 24.316109422492403,
          "left": 63.52941176470588,
          "width": 7.053475935828889,
          "height": 3.559270516717327
        },
        "id": "17",
        "kind": {
          "type": "fuse",
          "format": "mini",
          "amp": 10
        },
        "description": "RF Receiver, Ignition Key III. & Door Warning Switch"
      },
      {
        "layout": {
          "top": 24.316109422492403,
          "left": 74.75935828877004,
          "width": 7.053475935828889,
          "height": 3.559270516717327
        },
        "id": "18",
        "kind": {
          "type": "fuse",
          "format": "mini",
          "amp": 7.5
        },
        "description": "W/O IMMO. & Smart Key : ICM Relay Box (Burglar Alarm Relay) With IMMO. or Smart Key : INHIBIT_SW(POSITION_SW) -"
      },
      {
        "layout": {
          "top": 32.82674772036474,
          "left": 7.807486631016043,
          "width": 7.053475935828889,
          "height": 3.559270516717327
        },
        "id": "19",
        "kind": {
          "type": "fuse",
          "format": "mini",
          "amp": 10
        },
        "description": "Crash Pad Switch, Multipurpose Check Connector, Head Lamp Leveling Device Actuator LH/RH, Auto Head Lamp Leveling Device Module, Stop Lamp Switch,AFLS_UNIT, F_WATER_SNSR, GLOW_RLY_UNIT_METAL, FPAS_SNSR, DSL_BOX - - - -"
      },
      {
        "layout": {
          "top": 32.82674772036474,
          "left": 30.053475935828878,
          "width": 7.160427807486641,
          "height": 3.711246200607905
        },
        "id": "20",
        "kind": {
          "type": "fuse",
          "format": "mini",
          "amp": 10
        },
        "description": "Not Used",
        "relatedEntities": [
          "NOT_USED_FUSE"
        ]
      },
      {
        "layout": {
          "top": 32.82674772036474,
          "left": 52.406417112299465,
          "width": 7.053475935828889,
          "height": 3.559270516717327
        },
        "id": "21",
        "kind": {
          "type": "fuse",
          "format": "mini",
          "amp": 20
        },
        "description": "Sunroof_MTR"
      },
      {
        "layout": {
          "top": 32.82674772036474,
          "left": 74.6524064171123,
          "width": 7.160427807486641,
          "height": 3.711246200607905
        },
        "id": "22",
        "kind": {
          "type": "fuse",
          "format": "mini",
          "amp": 15
        },
        "description": "Rear Seat Warmer LH/RH"
      },
      {
        "layout": {
          "top": 41.33738601823708,
          "left": 7.807486631016043,
          "width": 7.053475935828889,
          "height": 3.559270516717327
        },
        "id": "23",
        "kind": {
          "type": "fuse",
          "format": "mini",
          "amp": 20
        },
        "description": "E/R Fuse & Relay Box (Fuse - ABS 3, SENSOR 5, TCU)",
        "relatedEntities": [
          "SISTEMA_ABS",
          "SENSOR",
          "LUZ_TESTIGO"
        ]
      },
      {
        "layout": {
          "top": 41.33738601823708,
          "left": 30.053475935828878,
          "width": 7.160427807486641,
          "height": 3.711246200607905
        },
        "id": "24",
        "kind": {
          "type": "fuse",
          "format": "mini",
          "amp": 7.5
        },
        "description": "E/R Fuse & Relay Box (Blower Relay), A/C Control Module, Cluster lonizer, DSL BOX(PTC) RLY) -",
        "relatedEntities": [
          "FUSIBLERA",
          "RELAY",
          "AIRE_ACONDICIONADO",
          "COMANDO_CLIMATIZADOR"
        ],
        "individualFusePages": [
          {
            "url": "/hyundai/santa-fe/info/fusebox/2017/air-conditioning-fuse",
            "urlWithAnchor": "/hyundai/santa-fe/info/fusebox/2017/air-conditioning-fuse#problems-article",
            "title": "Air conditioning fuse",
            "problemsTitle": "View problems with the air conditioning fuse"
          }
        ]
      },
      {
        "layout": {
          "top": 41.33738601823708,
          "left": 41.283422459893046,
          "width": 7.053475935828889,
          "height": 3.559270516717327
        },
        "id": "25",
        "kind": {
          "type": "fuse",
          "format": "mini",
          "amp": 15
        },
        "description": "Rear Wiper Relay, Rear Wiper Motor, Multifunction Switch, BCM",
        "relatedEntities": [
          "RELAY(protects=LIMPIA_PARABRISAS(ubicacion=PARTE_TRASERA))",
          "MOTOR_IMPULSOR(of=LIMPIA_PARABRISAS(ubicacion=PARTE_TRASERA))",
          "COMANDO_LUCES_VOLANTE",
          "MODULO_CARROCERIA"
        ]
      },
      {
        "layout": {
          "top": 41.33738601823708,
          "left": 52.406417112299465,
          "width": 7.053475935828889,
          "height": 3.711246200607905
        },
        "id": "26",
        "kind": {
          "type": "fuse",
          "format": "mini",
          "amp": 25
        },
        "description": "Smart Key Control Module",
        "relatedEntities": [
          "LLAVE_INTELIGENTE"
        ]
      },
      {
        "layout": {
          "top": 41.33738601823708,
          "left": 74.6524064171123,
          "width": 7.160427807486641,
          "height": 3.711246200607905
        },
        "id": "27",
        "kind": {
          "type": "fuse",
          "format": "mini",
          "amp": 20
        },
        "description": "Driver/Passenger Seat Warmer Module"
      },
      {
        "layout": {
          "top": 49.848024316109424,
          "left": 7.807486631016043,
          "width": 7.053475935828889,
          "height": 3.711246200607905
        },
        "id": "28",
        "kind": {
          "type": "fuse",
          "format": "mini",
          "amp": 7.5
        },
        "description": "A/C Control Module",
        "relatedEntities": [
          "AIRE_ACONDICIONADO",
          "COMANDO_CLIMATIZADOR"
        ],
        "individualFusePages": [
          {
            "url": "/hyundai/santa-fe/info/fusebox/2017/air-conditioning-fuse",
            "urlWithAnchor": "/hyundai/santa-fe/info/fusebox/2017/air-conditioning-fuse#problems-article",
            "title": "Air conditioning fuse",
            "problemsTitle": "View problems with the air conditioning fuse"
          }
        ]
      },
      {
        "layout": {
          "top": 49.848024316109424,
          "left": 30.053475935828878,
          "width": 7.160427807486641,
          "height": 3.711246200607905
        },
        "id": "29",
        "kind": {
          "type": "fuse",
          "format": "mini",
          "amp": 20
        },
        "description": "Front Power Outlet & Cigarette Lighter, Luggage Power Outlet"
      },
      {
        "layout": {
          "top": 49.848024316109424,
          "left": 41.283422459893046,
          "width": 7.053475935828889,
          "height": 3.711246200607905
        },
        "id": "30",
        "kind": {
          "type": "fuse",
          "format": "mini",
          "amp": 15
        },
        "description": "Multifunction Switch, E/R Fuse & Relay Box (Wiper HI Relay, IG 2 Relay)",
        "relatedEntities": [
          "COMANDO_LUCES_VOLANTE"
        ]
      },
      {
        "layout": {
          "top": 49.848024316109424,
          "left": 52.406417112299465,
          "width": 7.053475935828889,
          "height": 3.711246200607905
        },
        "id": "31",
        "kind": {
          "type": "fuse",
          "format": "mini",
          "amp": 20
        },
        "description": "Not Used",
        "relatedEntities": [
          "NOT_USED_FUSE"
        ]
      },
      {
        "layout": {
          "top": 49.848024316109424,
          "left": 74.6524064171123,
          "width": 7.160427807486641,
          "height": 3.711246200607905
        },
        "id": "32",
        "kind": {
          "type": "fuse",
          "format": "mini",
          "amp": 25
        },
        "description": "Passenger Door Module, Rear Power Window Switch RH",
        "relatedEntities": [
          "PUERTA(ubicacion=LADO_DERECHO)"
        ]
      },
      {
        "layout": {
          "top": 58.51063829787234,
          "left": 7.807486631016043,
          "width": 7.160427807486641,
          "height": 3.559270516717327
        },
        "id": "33",
        "kind": {
          "type": "fuse",
          "format": "mini",
          "amp": 10
        },
        "description": "A/C Control Module",
        "relatedEntities": [
          "AIRE_ACONDICIONADO",
          "COMANDO_CLIMATIZADOR"
        ],
        "individualFusePages": [
          {
            "url": "/hyundai/santa-fe/info/fusebox/2017/air-conditioning-fuse",
            "urlWithAnchor": "/hyundai/santa-fe/info/fusebox/2017/air-conditioning-fuse#problems-article",
            "title": "Air conditioning fuse",
            "problemsTitle": "View problems with the air conditioning fuse"
          }
        ]
      },
      {
        "id": "34",
        "kind": {
          "type": "fuse",
          "format": "mini"
        },
        "layout": {
          "top": 58.51063829787234,
          "left": 30.053475935828878,
          "width": 7.160427807486641,
          "height": 3.711246200607905
        },
        "relatedEntities": []
      },
      {
        "layout": {
          "top": 58.51063829787234,
          "left": 41.19237616385071,
          "width": 7.053475935828889,
          "height": 3.559270516717327
        },
        "id": "35",
        "kind": {
          "type": "fuse",
          "format": "mini",
          "amp": 7.5
        },
        "description": "Smart Key Control Module, Stop Lamp Switch",
        "relatedEntities": [
          "LLAVE_INTELIGENTE"
        ]
      },
      {
        "layout": {
          "top": 58.51063829787234,
          "left": 52.406417112299465,
          "width": 7.053475935828889,
          "height": 3.559270516717327
        },
        "id": "36",
        "kind": {
          "type": "fuse",
          "format": "mini",
          "amp": 20
        },
        "description": "SUNROOF MTR"
      },
      {
        "layout": {
          "top": 58.51063829787234,
          "left": 74.6524064171123,
          "width": 7.160427807486641,
          "height": 3.559270516717327
        },
        "id": "37",
        "kind": {
          "type": "fuse",
          "format": "mini",
          "amp": 25
        },
        "description": "Driver Safety Power Window Module, Driver Door Module, Rear Power Window Switch LH",
        "relatedEntities": [
          "PUERTA(ubicacion=LADO_IZQUIERDO)"
        ]
      },
      {
        "layout": {
          "top": 67.02127659574468,
          "left": 7.807486631016043,
          "width": 7.160427807486641,
          "height": 3.559270516717327
        },
        "id": "38",
        "kind": {
          "type": "fuse",
          "format": "mini",
          "amp": 15
        },
        "description": "Fuel Fillar Door Switch (DOOR_EXT)"
      },
      {
        "layout": {
          "top": 67.02127659574468,
          "left": 30.053475935828878,
          "width": 7.160427807486641,
          "height": 3.559270516717327
        },
        "id": "39",
        "kind": {
          "type": "fuse",
          "format": "mini",
          "amp": 10
        },
        "description": "Start/Stop Button Switch, Immobilizer Module",
        "relatedEntities": [
          "INMOVILIZADOR",
          "MODULO(of=INMOVILIZADOR)"
        ]
      },
      {
        "layout": {
          "top": 67.02127659574468,
          "left": 41.17647058823529,
          "width": 7.160427807486641,
          "height": 3.559270516717327
        },
        "id": "40",
        "kind": {
          "type": "fuse",
          "format": "mini",
          "amp": 15
        },
        "description": "Stop Signal Electronic Module"
      },
      {
        "layout": {
          "top": 67.02127659574468,
          "left": 52.406417112299465,
          "width": 7.053475935828889,
          "height": 3.559270516717327
        },
        "id": "41",
        "kind": {
          "type": "fuse",
          "format": "mini",
          "amp": 20
        },
        "description": "Passenger Seat Manual Switch, Passenger Lumbar Support Switch"
      },
      {
        "layout": {
          "top": 67.02127659574468,
          "left": 74.6524064171123,
          "width": 7.160427807486641,
          "height": 3.559270516717327
        },
        "id": "42",
        "kind": {
          "type": "fuse",
          "format": "mini",
          "amp": 30
        },
        "description": "AMP",
        "relatedEntities": [
          "AMPLIFICADOR"
        ]
      },
      {
        "layout": {
          "top": 75.53191489361703,
          "left": 30.053475935828878,
          "width": 7.160427807486641,
          "height": 3.559270516717327
        },
        "id": "43",
        "kind": {
          "type": "fuse",
          "format": "mini",
          "amp": 10
        },
        "description": "Audio, A/V & Navigation Head Unit, BCM, AMP, MTS Module, Power Outside Mirror Switch, E/R Fuse & Relay Box (Power Outlet Relay), AVM, D _CLOCK, USB CHARGE - -",
        "relatedEntities": [
          "ESTEREO",
          "MODULO_CARROCERIA",
          "AMPLIFICADOR",
          "INTERRUPTOR(of=ESPEJO_ELECTRICO)",
          "FUSIBLERA",
          "RELAY"
        ],
        "individualFusePages": [
          {
            "url": "/hyundai/santa-fe/info/fusebox/2017/radio-fuse",
            "urlWithAnchor": "/hyundai/santa-fe/info/fusebox/2017/radio-fuse#problems-article",
            "title": "Radio fuse",
            "problemsTitle": "View problems with the radio fuse"
          }
        ]
      },
      {
        "layout": {
          "top": 75.53191489361703,
          "left": 41.283422459893046,
          "width": 7.053475935828889,
          "height": 3.559270516717327
        },
        "id": "44",
        "kind": {
          "type": "fuse",
          "format": "mini",
          "amp": 20
        },
        "description": "Door Lock/Unlock Relay, Tail Gate Relay, ICM Relay Box (Dead Lock Relay)",
        "relatedEntities": [
          "RELAY(protects=PROP_OR(0=CIERRE_CENTRALIZADO,1=CIERRE_CENTRALIZADO))"
        ]
      },
      {
        "layout": {
          "top": 75.53191489361703,
          "left": 52.406417112299465,
          "width": 7.053475935828889,
          "height": 3.559270516717327
        },
        "id": "45",
        "kind": {
          "type": "fuse",
          "format": "mini",
          "amp": 30
        },
        "description": "Driver IMS Module, Driver Seat Manual Switch, Driver Lumbar Support Switch"
      },
      {
        "id": "Fuse switch",
        "kind": {
          "type": "other",
          "format": ""
        },
        "layout": {
          "top": 7.745088472744932,
          "left": 39.245112535359276,
          "width": 10.78733376248065,
          "height": 25.867233518715793
        },
        "relatedEntities": []
      }
    ],
    "boxDescription": "The fuse panel is located in the driver’s side panel bolster.",
    "boxName": "Fuse/Relay panel description",
    "boxDiagramImg": {
      "url": "https://startmycar-images.s3.amazonaws.com/manual-screenshots/6100532cdefea80004cff9ab/fragment-6100532cdefea80004cff9ab-b186b056da.jpg",
      "source": "611250730e33150004a615d9"
    },
    "boxTablesImages": [
      {
        "url": "https://startmycar-images.s3.amazonaws.com/manual-screenshots/6100532cdefea80004cff9ab/fragment-6100532cdefea80004cff9ab-7dad8f9068.jpg",
        "source": "6112507b0e33150004a615da"
      },
      {
        "url": "https://startmycar-images.s3.amazonaws.com/manual-screenshots/6100532cdefea80004cff9ab/fragment-6100532cdefea80004cff9ab-dae523a84f.jpg",
        "source": "611250820e33150004a615db"
      },
      {
        "url": "https://startmycar-images.s3.amazonaws.com/manual-screenshots/6100532cdefea80004cff9ab/fragment-6100532cdefea80004cff9ab-6aa2a7649f.jpg",
        "source": "611250890e33150004a615dc"
      }
    ],
    "processed": false,
    "boxAspectRatio": 0.7037433155080214,
    "templateId": "613a6cc957da1c0004f057da",
    "templateRenameMap": {
      "A/BAG IND": "1",
      "A/BAG": "2",
      "5MODULE": "3",
      "1 MODULE": "4",
      "FOG LAMP REAR": "5",
      "2MEMORY": "6",
      "2 SMART KEY": "7",
      "3MODULE": "8",
      "3SMART KEY": "39",
      "INTERIOR LAMP": "11",
      "MULTI MEDIA": "12",
      "MDPS": "13",
      "HTD STRG": "15",
      "FOG LAMP FRONT": "16",
      "1MEMORY": "17",
      "START": "18",
      "2MODULE": "19",
      "CORNERING LAMP": "20",
      "2SUNROOF": "21",
      "S/HEATER RR": "22",
      "IGN": "23",
      "1A/CON": "24",
      "WIPER RR": "25",
      "1SMART KEY": "26",
      "S/HEATER FRT": "27",
      "2A/CON": "28",
      "C/LIGHTER": "29",
      "WIPER FRT": "30",
      "A/CON RR": "31",
      "P/WDW RH": "32",
      "REAR HTD": "33",
      "BRAKE SWITCH": "35",
      "1SUNROOF": "36",
      "P/WDW LH": "37",
      "FUEL LID": "38",
      "4SMART KEY": "10",
      "STOP LAMP": "40",
      "P/SEAT (PASS)": "41",
      "AMP": "42",
      "4MODULE": "43",
      "DOOR LOCK": "44",
      "P/SEAT (DRV)": "45"
    },
    "backgroundColor": "#c6bd94",
    "imageClusters": [
      "61e1d1835132680004aa7b7e"
    ],
    "boxScaleMultiplier": "1",
    "fromManual": true,
    "boxThumbnail": "https://images.startmycar.com/legos/fusebox-thumbnails/fusebox-hyundai-santa-fe-2017-genid-g3-0.webp"
  },
  {
    "fuses": [
      {
        "layout": {
          "top": 17.232375979112273,
          "left": 35.88542141230066,
          "width": 7.061503416856492,
          "height": 5.091383812010443
        },
        "id": "E30",
        "kind": {
          "type": "relay",
          "format": "half"
        },
        "description": "POWER OUTLET RELAY",
        "relatedEntities": [
          "RELAY(protects=TOMA_12V)"
        ]
      },
      {
        "layout": {
          "top": 17.232375979112273,
          "left": 44.98861047835991,
          "width": 6.947608200455581,
          "height": 5.091383812010443
        },
        "id": "E31",
        "kind": {
          "type": "relay",
          "format": "half"
        },
        "description": "START RELAY"
      },
      {
        "layout": {
          "top": 19.451697127937337,
          "left": 60.820045558086555,
          "width": 7.175398633257403,
          "height": 6.135770234986945
        },
        "id": "E32",
        "kind": {
          "type": "relay",
          "format": "half"
        },
        "description": "FRONT DEICER RELAY"
      },
      {
        "layout": {
          "top": 27.23237597911227,
          "left": 60.820045558086555,
          "width": 7.175398633257403,
          "height": 6.266318537859007
        },
        "id": "E33",
        "kind": {
          "type": "relay",
          "format": "half"
        },
        "description": "BLOWER RELAY",
        "relatedEntities": [
          "RELAY(protects=VENTILADOR_DE_CLIMATIZADOR)"
        ]
      },
      {
        "layout": {
          "top": 35.14360313315927,
          "left": 60.820045558086555,
          "width": 7.175398633257403,
          "height": 6.135770234986945
        },
        "id": "E34",
        "kind": {
          "type": "relay",
          "format": "half"
        },
        "description": "WIPER LO RELAY"
      },
      {
        "layout": {
          "top": 42.9242819843342,
          "left": 60.820045558086555,
          "width": 7.175398633257403,
          "height": 6.266318537859007
        },
        "id": "E36",
        "kind": {
          "type": "relay",
          "format": "half"
        },
        "description": "ACC RELAY",
        "relatedEntities": [
          "RELAY(protects=GENERIC_FUSE_NAME)",
          "GENERIC_FUSE_NAME(protects=RELAY)"
        ]
      },
      {
        "layout": {
          "top": 50.90078328981723,
          "left": 60.820045558086555,
          "width": 7.175398633257403,
          "height": 6.005221932114883
        },
        "id": "E37",
        "kind": {
          "type": "relay",
          "format": "half"
        },
        "description": "IG1 RELAY",
        "relatedEntities": [
          "RELAY(protects=ACCESORIO_ELECTRICO)"
        ]
      },
      {
        "layout": {
          "top": 58.61618798955614,
          "left": 60.820045558086555,
          "width": 7.175398633257403,
          "height": 6.266318537859007
        },
        "id": "E38",
        "kind": {
          "type": "relay",
          "format": "half"
        },
        "description": "IG 2 RELAY"
      },
      {
        "layout": {
          "top": 58.25009945362207,
          "left": 70.15945330296127,
          "width": 7.6309794988610475,
          "height": 8.355091383812011
        },
        "id": "E39",
        "kind": {
          "type": "relay",
          "format": "full"
        },
        "description": "COOLING FAN RELAY",
        "relatedEntities": [
          "RELAY(protects=VENTILADOR_RADIADOR)"
        ],
        "individualFusePages": [
          {
            "url": "/hyundai/santa-fe/info/fusebox/2017/cooling-fan-relay",
            "urlWithAnchor": "/hyundai/santa-fe/info/fusebox/2017/cooling-fan-relay#problems-article",
            "title": "Cooling fan relay",
            "problemsTitle": "View problems with the cooling fan relay"
          }
        ]
      },
      {
        "layout": {
          "top": 69.62352880206514,
          "left": 62.281353895930096,
          "width": 7.175398633257403,
          "height": 6.266318537859007
        },
        "id": "E40",
        "kind": {
          "type": "relay",
          "format": "half"
        },
        "description": "WIPER HI RELAY"
      },
      {
        "layout": {
          "top": 69.7540771049372,
          "left": 70.72892938496584,
          "width": 7.061503416856492,
          "height": 6.135770234986945
        },
        "id": "E41",
        "kind": {
          "type": "relay",
          "format": "half"
        },
        "description": "REAR DEFOGGER RELAY",
        "relatedEntities": [
          "RELAY(protects=DESEMPANADOR_TRASERO)"
        ]
      },
      {
        "layout": {
          "top": 65.66579634464752,
          "left": 21.753986332574033,
          "width": 7.175398633257403,
          "height": 6.527415143603134
        },
        "id": "E42",
        "kind": {
          "type": "relay",
          "format": "half"
        },
        "description": "HORN RELAY",
        "relatedEntities": [
          "RELAY(protects=BOCINA)"
        ],
        "individualFusePages": [
          {
            "url": "/hyundai/santa-fe/info/fusebox/2017/horn-relay",
            "urlWithAnchor": "/hyundai/santa-fe/info/fusebox/2017/horn-relay#problems-article",
            "title": "Horn relay",
            "problemsTitle": "View problems with the horn relay"
          }
        ]
      },
      {
        "layout": {
          "top": 65.27415143603133,
          "left": 45.44419134396355,
          "width": 2.8971526195899786,
          "height": 6.146214099216708
        },
        "id": "MDPS",
        "kind": {
          "amp": 80,
          "type": "fuse-block",
          "format": "honda-generic"
        },
        "description": "MDPS Unit"
      },
      {
        "layout": {
          "top": 59.38082804923536,
          "left": 45.44419134396355,
          "width": 2.8971526195899786,
          "height": 6.146214099216708
        },
        "id": "2B+",
        "kind": {
          "amp": 60,
          "type": "fuse-block",
          "format": "honda-generic"
        },
        "description": "Smart J unction Box (IPS 1 (4CH), IPS 2 (1CH), IPS 5 (1CH), Fuse - SUNROOF 1, P/SEAT PASS, P/SEAT DRV), RR A/CON",
        "relatedEntities": [
          "FUSIBLE",
          "TECHO_SOLAR",
          "MARCHA_PARKING",
          "ASIENTO",
          "TESTIGO_DIRECCION_ASISTIDA",
          "ASIENTO_ELECTRICO(ubicacion=LADO_IZQUIERDO)"
        ]
      },
      {
        "layout": {
          "top": 53.487504662439385,
          "left": 45.44419134396355,
          "width": 2.8971526195899786,
          "height": 6.146214099216708
        },
        "id": "BLOWER",
        "kind": {
          "amp": 40,
          "type": "fuse-block",
          "format": "honda-generic"
        },
        "description": "Blower Relay",
        "relatedEntities": [
          "RELAY(protects=VENTILADOR_DE_CLIMATIZADOR)"
        ]
      },
      {
        "layout": {
          "top": 47.594181275643415,
          "left": 45.44419134396355,
          "width": 2.8971526195899786,
          "height": 6.146214099216708
        },
        "id": "RR HTD",
        "kind": {
          "amp": 40,
          "type": "fuse-block",
          "format": "honda-generic"
        },
        "description": "Rear Defogger Relay",
        "relatedEntities": [
          "RELAY(protects=DESEMPANADOR_TRASERO)"
        ]
      },
      {
        "layout": {
          "top": 41.700857888847445,
          "left": 45.44419134396355,
          "width": 2.8971526195899786,
          "height": 6.146214099216708
        },
        "id": "ABS1",
        "kind": {
          "amp": 40,
          "type": "fuse-block",
          "format": "honda-generic"
        },
        "description": "ESC Module, Multipurpose Check Connector",
        "relatedEntities": [
          "CONTROL_DE_ESTABILIDAD",
          "MODULO(of=CONTROL_DE_ESTABILIDAD)"
        ]
      },
      {
        "layout": {
          "top": 35.807534502051475,
          "left": 45.44419134396355,
          "width": 2.8971526195899786,
          "height": 6.146214099216708
        },
        "id": "ABS2",
        "kind": {
          "amp": 40,
          "type": "fuse-block",
          "format": "honda-generic"
        },
        "description": "ESC Module",
        "relatedEntities": [
          "CONTROL_DE_ESTABILIDAD",
          "MODULO(of=CONTROL_DE_ESTABILIDAD)"
        ]
      },
      {
        "layout": {
          "top": 29.914211115255505,
          "left": 45.44419134396355,
          "width": 2.8971526195899786,
          "height": 6.146214099216708
        },
        "id": "C/FAN",
        "kind": {
          "amp": 60,
          "type": "fuse-block",
          "format": "honda-generic"
        },
        "description": "Cooling Fan Relay",
        "relatedEntities": [
          "RELAY(protects=VENTILADOR_RADIADOR)"
        ]
      },
      {
        "layout": {
          "top": 24.020887728459535,
          "left": 45.44419134396355,
          "width": 2.8971526195899786,
          "height": 6.146214099216708
        },
        "id": "3B+",
        "kind": {
          "amp": 60,
          "type": "fuse-block",
          "format": "honda-generic"
        },
        "description": "Smart J unction Box (Fuse - MODULE 1, SMART KEY 4, SUNROOF 2, SMART KEY 1, Leak Current Autocut Device)",
        "relatedEntities": [
          "MODULO",
          "ECU",
          "LLAVE_INTELIGENTE",
          "TECHO_SOLAR"
        ]
      },
      {
        "layout": {
          "top": 63.18537859007834,
          "left": 53.18906605922551,
          "width": 5.6558086560364424,
          "height": 5.87467362924282
        },
        "id": "4B+",
        "kind": {
          "type": "fuse",
          "format": "cartridge-j",
          "amp": 50
        },
        "description": "Smart Junction Box (IPS 3 (4CH), IPS 6 (2CH), Fuse - F/LID, STOP LAMP, DR LOCK, BRAKE SWITCH), FUEL LID",
        "relatedEntities": [
          "FUSIBLE",
          "TESTIGO_STOP",
          "LAMPARA(of=LUZ_FRENO)",
          "LUZ_FRENO",
          "SENSOR_FRENO"
        ],
        "individualFusePages": [
          {
            "url": "/hyundai/santa-fe/info/fusebox/2017/brake-light-fuse",
            "urlWithAnchor": "/hyundai/santa-fe/info/fusebox/2017/brake-light-fuse#problems-article",
            "title": "Brake light fuse",
            "problemsTitle": "View problems with the brake light fuse"
          }
        ]
      },
      {
        "layout": {
          "top": 25.718015665796344,
          "left": 53.18906605922551,
          "width": 5.6558086560364424,
          "height": 5.87467362924282
        },
        "id": "ECU",
        "kind": {
          "type": "fuse",
          "format": "cartridge-j",
          "amp": 40
        },
        "description": "ECU Box"
      },
      {
        "layout": {
          "top": 44.38642297650131,
          "left": 53.18906605922551,
          "width": 5.6558086560364424,
          "height": 5.87467362924282
        },
        "id": "IG1",
        "kind": {
          "type": "fuse",
          "format": "cartridge-j",
          "amp": 40
        },
        "description": "W/O Smart Key : Ignition Switch, With Smart Key - ACC Relay, IG1 Relay",
        "relatedEntities": [
          "RELAY(protects=GENERIC_FUSE_NAME)",
          "GENERIC_FUSE_NAME(protects=RELAY)",
          "RELAY(protects=ACCESORIO_ELECTRICO)"
        ]
      },
      {
        "layout": {
          "top": 56.919060052219315,
          "left": 53.18906605922551,
          "width": 5.6558086560364424,
          "height": 5.87467362924282
        },
        "id": "IG2",
        "kind": {
          "type": "fuse",
          "format": "cartridge-j",
          "amp": 40
        },
        "description": "Start Relay, IG 2 Relay, W/O Smart Key : Ignition Switch"
      },
      {
        "layout": {
          "top": 62.263929736531956,
          "left": 38.382687927107064,
          "width": 4.441913439635535,
          "height": 4.960835509138381
        },
        "id": "TRAILER",
        "kind": {
          "type": "fuse",
          "format": "cartridge-j",
          "amp": 30
        },
        "description": "Trailer Power Outlet"
      },
      {
        "layout": {
          "top": 68.12010443864236,
          "left": 38.382687927107064,
          "width": 4.441913439635535,
          "height": 4.960835509138381
        },
        "id": "1B+",
        "kind": {
          "type": "fuse",
          "format": "cartridge-j",
          "amp": 50
        },
        "description": "Smart J unction Box (Fuse - S/HEATER R R , S/HEATER FRT, P/WDW RH, P/WDW LH)"
      },
      {
        "layout": {
          "top": 23.368146214099216,
          "left": 38.382687927107064,
          "width": 4.441913439635535,
          "height": 2.8720626631853787
        },
        "id": "HORN",
        "kind": {
          "type": "fuse",
          "format": "mini",
          "amp": 15
        },
        "description": "Horn Relay",
        "relatedEntities": [
          "RELAY(protects=BOCINA)"
        ],
        "individualFusePages": [
          {
            "url": "/hyundai/santa-fe/info/fusebox/2017/horn-fuse",
            "urlWithAnchor": "/hyundai/santa-fe/info/fusebox/2017/horn-fuse#problems-article",
            "title": "Horn fuse",
            "problemsTitle": "View problems with the horn fuse"
          }
        ]
      },
      {
        "layout": {
          "top": 38.98274867311811,
          "left": 38.382687927107064,
          "width": 4.328018223234624,
          "height": 2.741514360313316
        },
        "id": "DEICER",
        "kind": {
          "type": "fuse",
          "format": "mini",
          "amp": 15
        },
        "description": "Front Deicer Relay"
      },
      {
        "layout": {
          "top": 45.17085007922352,
          "left": 38.382687927107064,
          "width": 4.441913439635535,
          "height": 2.8720626631853787
        },
        "id": "POWER OUTLET",
        "kind": {
          "type": "fuse",
          "format": "mini",
          "amp": 25
        },
        "description": "Power Outlet Relay",
        "relatedEntities": [
          "RELAY(protects=TOMA_12V)"
        ],
        "individualFusePages": [
          {
            "url": "/hyundai/santa-fe/info/fusebox/2017/cigarette-lighter-fuse",
            "urlWithAnchor": "/hyundai/santa-fe/info/fusebox/2017/cigarette-lighter-fuse#problems-article",
            "title": "Cigarette lighter fuse",
            "problemsTitle": "View problems with the cigarette lighter fuse"
          }
        ]
      },
      {
        "layout": {
          "top": 73.89519060008882,
          "left": 38.382687927107064,
          "width": 4.441913439635535,
          "height": 4.960835509138381
        },
        "id": "AC INVERTER",
        "kind": {
          "type": "fuse",
          "format": "cartridge-j",
          "amp": 30
        },
        "description": "AC Inverter Module",
        "relatedEntities": [
          "INVERTER(of=AIRE_ACONDICIONADO)",
          "INVERTER"
        ]
      },
      {
        "layout": {
          "top": 50.796396812046616,
          "left": 53.18906605922551,
          "width": 5.6558086560364424,
          "height": 5.87467362924282
        },
        "id": "POWER TAILGATE",
        "kind": {
          "type": "fuse",
          "format": "cartridge-j",
          "amp": 30
        },
        "description": "Power Tail Gate Module"
      },
      {
        "layout": {
          "top": 57.702349869451695,
          "left": 38.382687927107064,
          "width": 4.441913439635535,
          "height": 2.8720626631853787
        },
        "id": "IDB",
        "kind": {
          "type": "fuse",
          "format": "mini",
          "amp": 15
        },
        "description": "IDB Module"
      },
      {
        "layout": {
          "top": 48.26490078227622,
          "left": 38.382687927107064,
          "width": 4.441913439635535,
          "height": 2.8720626631853787
        },
        "id": "4WD",
        "kind": {
          "type": "fuse",
          "format": "mini",
          "amp": 20
        },
        "description": "4WD ECM"
      },
      {
        "layout": {
          "top": 51.92150615861123,
          "left": 38.382687927107064,
          "width": 4.441913439635535,
          "height": 2.8720626631853787
        },
        "id": "AMS",
        "kind": {
          "type": "fuse",
          "format": "mini",
          "amp": 10
        },
        "description": "Battery Sensor",
        "relatedEntities": [
          "TESTIGO_BATERIA"
        ]
      },
      {
        "layout": {
          "top": 57.547052891434326,
          "left": 21.127765866145033,
          "width": 2.6993865030674833,
          "height": 5.6255467328231035
        },
        "id": "AMS (WIPER)",
        "kind": {
          "type": "fuse",
          "format": "mini",
          "amp": 10
        },
        "description": "BCM, PCM",
        "relatedEntities": [
          "MODULO_CARROCERIA",
          "PCM"
        ]
      },
      {
        "layout": {
          "top": 57.547052891434326,
          "left": 24.072551142218654,
          "width": 2.6993865030674833,
          "height": 5.6255467328231035
        },
        "id": "WIPER FRT",
        "kind": {
          "type": "fuse",
          "format": "mini",
          "amp": 25
        },
        "description": "Wiper LO Relay, Front Wiper Motor",
        "relatedEntities": [
          "MOTOR_IMPULSOR(of=LIMPIA_PARABRISAS(ubicacion=PARTE_DELANTERA))"
        ]
      },
      {
        "layout": {
          "top": 57.547052891434326,
          "left": 26.771937645286137,
          "width": 2.6993865030674833,
          "height": 5.6255467328231035
        },
        "id": "B/UP LAMP",
        "kind": {
          "type": "fuse",
          "format": "mini",
          "amp": 10
        },
        "description": "A/T - Rear Combination Lamp (IN) LH/RH, Electro Chromic Mirror, Audio, A/V & Navigation Head Unit",
        "relatedEntities": [
          "ESTEREO"
        ],
        "individualFusePages": [
          {
            "url": "/hyundai/santa-fe/info/fusebox/2017/radio-fuse",
            "urlWithAnchor": "/hyundai/santa-fe/info/fusebox/2017/radio-fuse#problems-article",
            "title": "Radio fuse",
            "problemsTitle": "View problems with the radio fuse"
          }
        ]
      },
      {
        "layout": {
          "top": 57.547052891434326,
          "left": 29.471324148353624,
          "width": 2.6993865030674833,
          "height": 5.6255467328231035
        },
        "id": "ABS3",
        "kind": {
          "type": "fuse",
          "format": "mini",
          "amp": 7.5
        },
        "description": "ESC Module",
        "relatedEntities": [
          "CONTROL_DE_ESTABILIDAD",
          "MODULO(of=CONTROL_DE_ESTABILIDAD)"
        ]
      },
      {
        "layout": {
          "top": 57.547052891434326,
          "left": 31.925311878414973,
          "width": 2.6993865030674833,
          "height": 5.6255467328231035
        },
        "id": "5 SENSOR",
        "kind": {
          "type": "fuse",
          "format": "mini",
          "amp": 7.5
        },
        "description": "PCM",
        "relatedEntities": [
          "PCM"
        ]
      },
      {
        "layout": {
          "top": 57.547052891434326,
          "left": 34.62469838148246,
          "width": 2.6993865030674833,
          "height": 5.6255467328231035
        },
        "id": "TCU",
        "kind": {
          "type": "fuse",
          "format": "mini",
          "amp": 15
        },
        "description": "A/T : Transaxle Range Switch"
      },
      {
        "layout": {
          "top": 22.106108474648824,
          "left": 77.32408488454993,
          "width": 5.153374233128844,
          "height": 4.781714722899633
        },
        "id": "F/PUMP",
        "kind": {
          "type": "fuse",
          "format": "mini",
          "amp": 15
        },
        "description": "Fuel Pump Relay",
        "relatedEntities": [
          "RELAY(protects=BOMBA_DE_COMBUSTIBLE)",
          "RELAY(protects=BOMBA(fluid=COMBUSTIBLE))"
        ],
        "individualFusePages": [
          {
            "url": "/hyundai/santa-fe/info/fusebox/2017/fuel-pump-fuse",
            "urlWithAnchor": "/hyundai/santa-fe/info/fusebox/2017/fuel-pump-fuse#problems-article",
            "title": "Fuel pump fuse",
            "problemsTitle": "View problems with the fuel pump fuse"
          }
        ]
      },
      {
        "layout": {
          "top": 26.887823197548457,
          "left": 77.32408488454993,
          "width": 5.153374233128844,
          "height": 4.781714722899633
        },
        "id": "1ECU",
        "kind": {
          "type": "fuse",
          "format": "mini",
          "amp": 15
        },
        "description": "PCM",
        "relatedEntities": [
          "PCM"
        ]
      },
      {
        "layout": {
          "top": 22.106108474648824,
          "left": 70.45291924037817,
          "width": 5.153374233128844,
          "height": 4.781714722899633
        },
        "id": "2ECU",
        "kind": {
          "type": "fuse",
          "format": "mini",
          "amp": 10
        },
        "description": "IDB Module"
      },
      {
        "layout": {
          "top": 26.887823197548457,
          "left": 70.45291924037817,
          "width": 5.153374233128844,
          "height": 4.781714722899633
        },
        "id": "3 SENSOR",
        "kind": {
          "type": "fuse",
          "format": "mini",
          "amp": 10
        },
        "description": "Fuel Pump Relay",
        "relatedEntities": [
          "RELAY(protects=BOMBA_DE_COMBUSTIBLE)",
          "RELAY(protects=BOMBA(fluid=COMBUSTIBLE))"
        ],
        "individualFusePages": [
          {
            "url": "/hyundai/santa-fe/info/fusebox/2017/fuel-pump-fuse",
            "urlWithAnchor": "/hyundai/santa-fe/info/fusebox/2017/fuel-pump-fuse#problems-article",
            "title": "Fuel pump fuse",
            "problemsTitle": "View problems with the fuel pump fuse"
          }
        ]
      },
      {
        "layout": {
          "top": 31.669537920448086,
          "left": 70.45291924037817,
          "width": 5.153374233128844,
          "height": 4.781714722899633
        },
        "id": "IGN COIL",
        "kind": {
          "type": "fuse",
          "format": "mini",
          "amp": 20
        },
        "description": "Condenser, Ignition Coil #1/#2/#3/#4"
      },
      {
        "layout": {
          "top": 36.16997530670656,
          "left": 70.45291924037817,
          "width": 5.153374233128844,
          "height": 4.781714722899633
        },
        "id": "2 SENSOR",
        "kind": {
          "type": "fuse",
          "format": "mini",
          "amp": 10
        },
        "description": "Purge Control Solenoid Valve, Variable Intake Solenoid Valve(G4KJ) Oil Control Valve #1/#2",
        "relatedEntities": [
          "VALVULA_PURGA_CANISTER"
        ]
      },
      {
        "layout": {
          "top": 40.670412692965044,
          "left": 70.45291924037817,
          "width": 5.153374233128844,
          "height": 4.781714722899633
        },
        "id": "1 SENSOR",
        "kind": {
          "type": "fuse",
          "format": "mini",
          "amp": 15
        },
        "description": "Oxygen sensor( #1/#2/#3/#4), PCM, Oxygen Sensor(Down), E/R Fuse & Relay Box (Cooling Fan Relay)",
        "relatedEntities": [
          "PCM",
          "FUSIBLERA",
          "RELAY"
        ]
      },
      {
        "layout": {
          "top": 54.73427952502278,
          "left": 38.382687927107064,
          "width": 4.441913439635535,
          "height": 2.8720626631853787
        },
        "id": "B/A HORN",
        "kind": {
          "type": "fuse",
          "format": "mini",
          "amp": 10
        },
        "description": "Burgl Aralarm Horn Relay"
      },
      {
        "id": "SPARE 1",
        "kind": {
          "type": "fuse",
          "format": "mini"
        },
        "layout": {
          "top": 73.43443362330548,
          "left": 20.95909136734701,
          "width": 2.9488695338160857,
          "height": 6.966948254626858
        }
      },
      {
        "id": "SPARE 2",
        "kind": {
          "type": "fuse",
          "format": "mini"
        },
        "layout": {
          "top": 73.43533387397852,
          "left": 23.745870669197767,
          "width": 2.9488695338160857,
          "height": 6.966948254626858
        }
      },
      {
        "id": "SPARE 3",
        "kind": {
          "type": "fuse",
          "format": "mini"
        },
        "layout": {
          "top": 73.44121786367027,
          "left": 26.532649971048524,
          "width": 2.9488695338160857,
          "height": 6.966948254626858
        }
      },
      {
        "id": "SPARE 4",
        "kind": {
          "type": "fuse",
          "format": "mini"
        },
        "layout": {
          "top": 73.44667003406614,
          "left": 29.31942927289928,
          "width": 2.9488695338160857,
          "height": 6.966948254626858
        }
      },
      {
        "id": "SPARE 5",
        "kind": {
          "type": "fuse",
          "format": "mini"
        },
        "layout": {
          "top": 73.36132406536623,
          "left": 32.106208574750035,
          "width": 2.9488695338160857,
          "height": 6.966948254626858
        }
      },
      {
        "id": "SPARE 6",
        "kind": {
          "type": "fuse",
          "format": "mini"
        },
        "layout": {
          "top": 73.34998790527854,
          "left": 34.89298787660075,
          "width": 2.9488695338160857,
          "height": 6.966948254626858
        }
      },
      {
        "id": "FUSE PULLER",
        "kind": {
          "type": "fusepuller",
          "format": "",
          "notUsed": false
        },
        "layout": {
          "top": 58.803958007303336,
          "left": 79.23887712587117,
          "width": 5.870932331360876,
          "height": 6.885758998435055
        }
      },
      {
        "id": "4 SENSOR",
        "kind": {
          "type": "fuse",
          "format": "mini"
        },
        "layout": {
          "top": 45.76558786877606,
          "left": 70.34577375212312,
          "width": 5.467665467157785,
          "height": 4.344635715527739
        }
      },
      {
        "id": "H/LAMP HI",
        "kind": {
          "type": "fuse",
          "format": "mini"
        },
        "layout": {
          "top": 50.27677149776689,
          "left": 70.50721560951544,
          "width": 5.338850954209092,
          "height": 4.4862033679882485
        }
      }
    ],
    "boxDescription": "The fuse panel is located in the engine compartment near the battery.",
    "boxName": "Engine compartment fuse panel ",
    "boxDiagramImg": {
      "url": "https://startmycar-images.s3.amazonaws.com/manual-screenshots/6100532cdefea80004cff9ab/fragment-6100532cdefea80004cff9ab-f545c46760.jpg",
      "source": "611250980e33150004a615dd"
    },
    "boxTablesImages": [
      {
        "url": "https://startmycar-images.s3.amazonaws.com/manual-screenshots/6100532cdefea80004cff9ab/fragment-6100532cdefea80004cff9ab-0aa293c495.jpg",
        "source": "611250a00e33150004a615de"
      },
      {
        "url": "https://startmycar-images.s3.amazonaws.com/manual-screenshots/6100532cdefea80004cff9ab/fragment-6100532cdefea80004cff9ab-8057fd211d.jpg",
        "source": "611250a90e33150004a615df"
      },
      {
        "url": "https://startmycar-images.s3.amazonaws.com/manual-screenshots/6100532cdefea80004cff9ab/fragment-6100532cdefea80004cff9ab-46ce94095f.jpg",
        "source": "611250b20e33150004a615e0"
      }
    ],
    "processed": false,
    "boxAspectRatio": 0.7546362339514978,
    "templateId": "613a6ce357da1c0004f057db",
    "boxScaleMultiplier": "0.9",
    "fromManual": true,
    "boxThumbnail": "https://images.startmycar.com/legos/fusebox-thumbnails/fusebox-hyundai-santa-fe-2017-genid-g3-1.webp"
  }
]